{"inkVersion":20,"root":[[{"->":"tance"},["done",{"#f":5,"#n":"g-0"}],null],"done",{"tance":["^探测我之前进行过模拟操作了，师傅。",{"#":"speaker:你"},{"#":"portrait:A2"},{"#":"layout:left"},"\n","^说了多少次了，读万卷书，行万里路，你不缺理论知识，但是实践呢？",{"#":"speaker:白猿"},{"#":"portrait:B"},{"#":"layout:right"},"\n","^简单来说，探测就是发送多个信标，寻找遗迹的信号。",{"#":"speaker:你"},{"#":"portrait:A2"},{"#":"layout:left"},"\n","^当两个信标的探测范围套住了目标点，我们就可以发射探测器了。",{"#":"speaker:你"},{"#":"portrait:A2"},{"#":"layout:left"},"\n","^还有什么吗？",{"#":"speaker:白猿"},{"#":"portrait:B"},{"#":"layout:right"},"\n","^信标不能放置太近，信标放置数量有限，这是防止我们浪费信标。",{"#":"speaker:你"},{"#":"portrait:A2"},{"#":"layout:left"},"\n","^背的挺好，丫头，让我看看你的实操吧",{"#":"speaker:白猿"},{"#":"portrait:B"},{"#":"layout:right"},"\n","end",{"#f":1}],"#f":1}],"listDefs":{}}